pingsafe_cli/__init__.py
pingsafe_cli/scanner/__init__.py
pingsafe_cli/scanner/cli/__init__.py
pingsafe_cli/scanner/cli/codescanner/__init__.py
pingsafe_cli/scanner/cli/codescanner/code_scanner.py
pingsafe_cli/scanner/cli/codescanner/secret.py
pingsafe_cli/scanner/cli/command_line_arguments.py
pingsafe_cli/scanner/cli/config/__init__.py
pingsafe_cli/scanner/cli/config/config.py
pingsafe_cli/scanner/cli/main.py
pingsafe_cli/scanner/cli/registry.py
pingsafe_cli/scanner/cli/utils.py
pingsafe_cli/sentry.py
pingsafe_cli/version.py
pingsafe_cli-0.0.4.dist-info/LICENSE
pingsafe_cli-0.0.4.dist-info/METADATA
pingsafe_cli-0.0.4.dist-info/WHEEL
pingsafe_cli-0.0.4.dist-info/entry_points.txt
pingsafe_cli-0.0.4.dist-info/RECORD
