Metadata-Version: 2.1
Name: pingsafe-cli
Version: 0.0.4
Summary: PingSafe CLI is an extension of our vision to shift-left security with PingSafe.
License: Proprietary
Author: pingsafe-dev
Author-email: dev@pingsafe.com
Requires-Python: >=3.7.1,<4.0.0
Classifier: License :: Other/Proprietary License
Classifier: Programming Language :: Python :: 3
Classifier: Programming Language :: Python :: 3.8
Classifier: Programming Language :: Python :: 3.9
Classifier: Programming Language :: Python :: 3.10
Classifier: Programming Language :: Python :: 3.11
Requires-Dist: jsonschema (==4.17.3)
Requires-Dist: requests (==2.29.0)
Requires-Dist: sentry-sdk (>=1.24.0,<2.0.0)
Requires-Dist: toml (==0.10.2)
